zing/zing.py
zing/__init__.py
zing-0.0.2.dist-info/WHEEL
zing-0.0.2.dist-info/DESCRIPTION.rst
zing-0.0.2.dist-info/top_level.txt
zing-0.0.2.dist-info/RECORD
zing-0.0.2.dist-info/entry_points.txt
zing-0.0.2.dist-info/metadata.json
zing-0.0.2.dist-info/METADATA
