Metadata-Version: 2.0
Name: zing
Version: 0.0.2
Summary: a virtual beeper
Home-page: UNKNOWN
Author: Emanuel Schmid
Author-email: UNKNOWN
License: BSD
Platform: UNKNOWN
